gptspeak/__init__.py
gptspeak/cli.py
gptspeak/config/__init__.py
gptspeak/config/logging_config.py
gptspeak/core/__init__.py
gptspeak/core/converter.py
gptspeak/core/player.py
gptspeak/exceptions.py
gptspeak/utils/__init__.py
gptspeak/utils/api_utils.py
gptspeak/utils/file_utils.py
gptspeak-0.1.3.dist-info/LICENSE
gptspeak-0.1.3.dist-info/METADATA
gptspeak-0.1.3.dist-info/WHEEL
gptspeak-0.1.3.dist-info/entry_points.txt
gptspeak-0.1.3.dist-info/RECORD
