Metadata-Version: 2.1
Name: gptspeak
Version: 0.1.3
Summary: Text-to-speech CLI tool and Python library using OpenAI's TTS API
Author: Sanjay Nadhavajhala
Author-email: sanjay.nadhavajhala@gmail.com
Requires-Python: >=3.9,<4.0
Classifier: Programming Language :: Python :: 3
Classifier: Programming Language :: Python :: 3.9
Classifier: Programming Language :: Python :: 3.10
Classifier: Programming Language :: Python :: 3.11
Classifier: Programming Language :: Python :: 3.12
Classifier: Programming Language :: Python :: 3.13
Requires-Dist: click (>=8.1.7,<9.0.0)
Requires-Dist: openai (>=1.52.0,<2.0.0)
Requires-Dist: pydub (>=0.25.1,<0.26.0)
Requires-Dist: python-dotenv (>=1.0.1,<2.0.0)
Requires-Dist: simpleaudio (>=1.0.4,<2.0.0)
Requires-Dist: tqdm (>=4.66.5,<5.0.0)
